amuesm/__init__.py
amuesm/__main__.py
amuesm-3.11.dist-info/METADATA
amuesm-3.11.dist-info/WHEEL
amuesm-3.11.dist-info/entry_points.txt
amuesm-3.11.dist-info/licenses/LICENSE
amuesm-3.11.dist-info/RECORD
