Metadata-Version: 2.4
Name: amuesm
Version: 3.11
Summary: A module used to create random passwords with customizable options and to encode/decode strings!
Project-URL: BugTracker, https://github.com/AnniePrograms/amuesm/issues
Project-URL: Repository, https://github.com/AnniePrograms/amuesm.git
Author-email: Annie <SocializingAnnie@gmail.com>
License: MIT
License-File: LICENSE
Requires-Python: >=3.8
